boto3_type/__init__.py
boto3_type/client.py
boto3_type/common.py
boto3_type/resource.py
boto3_type/s3.py
boto3_type-0.1.0.dist-info/LICENSE
boto3_type-0.1.0.dist-info/METADATA
boto3_type-0.1.0.dist-info/WHEEL
boto3_type-0.1.0.dist-info/top_level.txt
boto3_type-0.1.0.dist-info/RECORD
