Metadata-Version: 2.1
Name: boto3-type
Version: 0.1.0
Summary: Boto3 service type check
Home-page: https://github.com/j4c0bs/boto3-type
Author: Jeremy Jacobs
Author-email: pub@j4c0bs.net
License: BSD-2-Clause
Project-URL: Source, https://github.com/j4c0bs/boto3-type
Project-URL: Bug Reports, https://github.com/j4c0bs/boto3-type/issues
Keywords: aws boto3 botocore
Platform: UNKNOWN
Classifier: Development Status :: 4 - Beta
Classifier: Intended Audience :: Developers
Classifier: License :: OSI Approved :: Apache Software License
Classifier: Programming Language :: Python
Classifier: Programming Language :: Python :: 3
Classifier: Programming Language :: Python :: 3.4
Classifier: Programming Language :: Python :: 3.5
Classifier: Programming Language :: Python :: 3.6
Classifier: Programming Language :: Python :: 3.7
Classifier: Programming Language :: Python :: 3.8
Requires-Python: >=3
Requires-Dist: boto3
Requires-Dist: botocore
